{
  "document_metadata": {
    "jurisdiction": "Halifax Regional Municipality",
    "bylaw_name": "Land Use By-law for Beaver Bank, Hammonds Plains and Upper Sackville",
    "source_document_path": "docs/beaverbank-hammondsplains-uppersackville-land-use-bylaw.pdf",
    "zone_code": "R-3",
    "zone_name": "MOBILE DWELLING",
    "part_label_raw": "PART 9"
  },
  "normalization_policy": {
    "clause_labels_preserved_raw": true,
    "approved_hierarchy_examples": [
      "21(e)",
      "21(ea)",
      "21(ea)(1)"
    ],
    "pending_review_clause_patterns": [
      "9.2",
      "9.3"
    ]
  },
  "permitted_uses": [
    {
      "clause_label_raw": null,
      "clause_path": null,
      "use_type": "residential_use",
      "status": "active",
      "citations": {
        "pdf_page_start": 62,
        "pdf_page_end": 62,
        "bylaw_page_start": 54,
        "bylaw_page_end": 54
      },
      "source_category_raw": null,
      "use_name": "Single unit dwellings"
    },
    {
      "clause_label_raw": null,
      "clause_path": null,
      "use_type": "residential_use",
      "status": "active",
      "citations": {
        "pdf_page_start": 62,
        "pdf_page_end": 62,
        "bylaw_page_start": 54,
        "bylaw_page_end": 54
      },
      "source_category_raw": null,
      "use_name": "Two unit dwellings"
    },
    {
      "clause_label_raw": null,
      "clause_path": null,
      "use_type": "residential_use",
      "status": "active",
      "citations": {
        "pdf_page_start": 62,
        "pdf_page_end": 62,
        "bylaw_page_start": 54,
        "bylaw_page_end": 54
      },
      "source_category_raw": null,
      "use_name": "Multiple unit dwellings containing 3 or 4 dwelling units within the Urban Service Area (RC-May 23/24;E-June 13/24)"
    },
    {
      "clause_label_raw": null,
      "clause_path": null,
      "use_type": "residential_use",
      "status": "active",
      "citations": {
        "pdf_page_start": 62,
        "pdf_page_end": 62,
        "bylaw_page_start": 54,
        "bylaw_page_end": 54
      },
      "source_category_raw": null,
      "use_name": "Shared housing use with 10 or fewer bedrooms in conjunction with a permitted dwelling unit (RC-Aug 9/22;E-Sep 15/22)"
    },
    {
      "clause_label_raw": null,
      "clause_path": null,
      "use_type": "principal_use",
      "status": "active",
      "citations": {
        "pdf_page_start": 62,
        "pdf_page_end": 62,
        "bylaw_page_start": 54,
        "bylaw_page_end": 54
      },
      "source_category_raw": null,
      "use_name": "Day care facilities for not more than fourteen (14) children and in conjunction with permitted dwellings"
    },
    {
      "clause_label_raw": null,
      "clause_path": null,
      "use_type": "residential_use",
      "status": "active",
      "citations": {
        "pdf_page_start": 62,
        "pdf_page_end": 62,
        "bylaw_page_start": 54,
        "bylaw_page_end": 54
      },
      "source_category_raw": null,
      "use_name": "Business uses in conjunction with permitted dwellings"
    },
    {
      "clause_label_raw": null,
      "clause_path": null,
      "use_type": "principal_use",
      "status": "active",
      "citations": {
        "pdf_page_start": 62,
        "pdf_page_end": 62,
        "bylaw_page_start": 54,
        "bylaw_page_end": 54
      },
      "source_category_raw": null,
      "use_name": "Open space uses"
    }
  ],
  "requirement_sections": [
    {
      "order_index": 1,
      "section_label_raw": "9.2",
      "title_label_raw": "R-3 ZONE REQUIREMENTS",
      "citations": {
        "pdf_page_start": 62,
        "pdf_page_end": 62,
        "bylaw_page_start": 54,
        "bylaw_page_end": 54
      },
      "provisions": [
        {
          "provision_label_raw": "9.2",
          "text": "R-3 ZONE REQUIREMENTS In any R -3 Zone, no development permit shall be issued except in conformity with the following: Minimum Lot Area 29,064 square feet (2700 m2) Minimum Frontage 100 feet (30.5 m) Minimum Front or Flankage Yard 20 feet (6.1 m) Minimum Rear or Side Yard 8 feet (2.4 m) Maximum Lot Coverage 35 per cent Maximum Height of Main Building 35 feet (10.7 m)",
          "status": "active",
          "citations": {
            "pdf_page_start": 62,
            "pdf_page_end": 62,
            "bylaw_page_start": 54,
            "bylaw_page_end": 54
          }
        }
      ]
    },
    {
      "order_index": 2,
      "section_label_raw": "9.3",
      "title_label_raw": "OTHER REQUIREMENTS: BUSINESS AND DAY CARE USES",
      "citations": {
        "pdf_page_start": 62,
        "pdf_page_end": 62,
        "bylaw_page_start": 54,
        "bylaw_page_end": 54
      },
      "provisions": [
        {
          "provision_label_raw": "9.3",
          "text": "OTHER REQUIREMENTS: BUSINESS AND DAY CARE USES Where business uses and day care facilities are permitted in any R-3 Zone, the provisions of Parts 11.3 and 11.4 shall apply.",
          "status": "active",
          "citations": {
            "pdf_page_start": 62,
            "pdf_page_end": 62,
            "bylaw_page_start": 54,
            "bylaw_page_end": 54
          }
        }
      ]
    }
  ],
  "content_blocks": [
    {
      "heading_context_raw": null,
      "text": "No development permit shall be issued in any R -3 (Mobile Dwelling Subdivision) Zone"
    },
    {
      "heading_context_raw": "except for the following:",
      "text": ""
    },
    {
      "heading_context_raw": "9.2 R-3 ZONE REQUIREMENTS",
      "text": "In any R -3 Zone, no development permit shall be issued except in conformity with the"
    },
    {
      "heading_context_raw": "following:",
      "text": "Minimum Lot Area 29,064 square feet (2700 m2) Minimum Frontage 100 feet (30.5 m) Minimum Front or Flankage Yard 20 feet (6.1 m) Minimum Rear or Side Yard 8 feet (2.4 m) Maximum Lot Coverage 35 per cent Maximum Height of Main Building 35 feet (10.7 m)"
    },
    {
      "heading_context_raw": "9.3 OTHER REQUIREMENTS: BUSINESS AND DAY CARE USES",
      "text": "Where business uses and day care facilities are permitted in any R-3 Zone, the provisions of Parts 11.3 and 11.4 shall apply."
    }
  ],
  "open_issues": [
    {
      "issue_type": "normalization_review",
      "description": "Clause patterns listed in pending_review_clause_patterns were preserved raw because their hierarchy normalization is not yet approved in this repository context."
    }
  ],
  "citations": {
    "zone_section": {
      "pdf_page_start": 62,
      "pdf_page_end": 62,
      "bylaw_page_start": 54,
      "bylaw_page_end": 54
    }
  }
}
