{
  "document_metadata": {
    "jurisdiction": "City of Charlottetown",
    "bylaw_name": "Zoning & Development Bylaw (PH-ZD.2 rev 049)",
    "source_document_path": "docs/charlottetown/charlottetown-zoning-bylaw.pdf",
    "zone_code": "WF",
    "zone_name": "WATERFRONT ZONE",
    "part_label_raw": "34",
    "chapter_heading_raw": "34 WATERFRONT ZONE (WF)"
  },
  "normalization_policy": {
    "clause_labels_preserved_raw": true,
    "approved_hierarchy_examples": [
      "21(e)",
      "21(ea)",
      "21(ea)(1)",
      "20(1)(a.1)"
    ],
    "pending_review_clause_patterns": []
  },
  "permitted_uses": [
    {
      "clause_label_raw": "34.1.1",
      "use_type": "principal_use",
      "use_name": "All uses as permitted in the Downtown Core (DC) Zone",
      "status": "active",
      "citations": {
        "pdf_page_start": 100,
        "pdf_page_end": 100,
        "bylaw_page_start": 100,
        "bylaw_page_end": 100
      },
      "clause_path": [
        "34.1.1"
      ]
    },
    {
      "clause_label_raw": "34.1.2",
      "use_type": "principal_use",
      "use_name": "Limited Car Rental Operation",
      "status": "active",
      "citations": {
        "pdf_page_start": 100,
        "pdf_page_end": 100,
        "bylaw_page_start": 100,
        "bylaw_page_end": 100
      },
      "clause_path": [
        "34.1.2"
      ]
    },
    {
      "clause_label_raw": "34.1.3",
      "use_type": "principal_use",
      "use_name": "Marina",
      "status": "active",
      "citations": {
        "pdf_page_start": 100,
        "pdf_page_end": 100,
        "bylaw_page_start": 100,
        "bylaw_page_end": 100
      },
      "clause_path": [
        "34.1.3"
      ]
    }
  ],
  "requirement_sections": [
    {
      "order_index": 1,
      "section_label_raw": "34.1",
      "title_label_raw": "PERMITTED USES",
      "citations": {
        "pdf_page_start": 100,
        "pdf_page_end": 100,
        "bylaw_page_start": 100,
        "bylaw_page_end": 100
      },
      "provisions": [
        {
          "provision_label_raw": "34.1.1",
          "clause_path": [
            "34.1.1"
          ],
          "text": "All uses as permitted in the Downtown Core (DC) Zone;",
          "status": "active",
          "citations": {
            "pdf_page_start": 100,
            "pdf_page_end": 100,
            "bylaw_page_start": 100,
            "bylaw_page_end": 100
          }
        },
        {
          "provision_label_raw": "34.1.2",
          "clause_path": [
            "34.1.2"
          ],
          "text": "Limited Car Rental Operation; and",
          "status": "active",
          "citations": {
            "pdf_page_start": 100,
            "pdf_page_end": 100,
            "bylaw_page_start": 100,
            "bylaw_page_end": 100
          }
        },
        {
          "provision_label_raw": "34.1.3",
          "clause_path": [
            "34.1.3"
          ],
          "text": "Marina",
          "status": "active",
          "citations": {
            "pdf_page_start": 100,
            "pdf_page_end": 100,
            "bylaw_page_start": 100,
            "bylaw_page_end": 100
          }
        }
      ]
    },
    {
      "order_index": 2,
      "section_label_raw": "34.2",
      "title_label_raw": "PERMITTED LAND USES AT GRADE ON WALKABLE STREETS",
      "citations": {
        "pdf_page_start": 100,
        "pdf_page_end": 100,
        "bylaw_page_start": 100,
        "bylaw_page_end": 100
      },
      "provisions": [
        {
          "provision_label_raw": "34.2.1",
          "clause_path": [
            "34.2.1"
          ],
          "text": "Only those uses listed below shall be permitted on the ground floor of a Building in the WF Zone immediately abutting a designated Walkable Street (Map C):",
          "status": "active",
          "citations": {
            "pdf_page_start": 100,
            "pdf_page_end": 100,
            "bylaw_page_start": 100,
            "bylaw_page_end": 100
          }
        },
        {
          "provision_label_raw": "a",
          "clause_path": [
            "34.2.1",
            "a"
          ],
          "text": "Eating and Drinking Establishments;",
          "status": "active",
          "citations": {
            "pdf_page_start": 100,
            "pdf_page_end": 100,
            "bylaw_page_start": 100,
            "bylaw_page_end": 100
          }
        },
        {
          "provision_label_raw": "b",
          "clause_path": [
            "34.2.1",
            "b"
          ],
          "text": "Tourism related services including but not limited to, information services, touring services, or personal equipment rentals;",
          "status": "active",
          "citations": {
            "pdf_page_start": 100,
            "pdf_page_end": 100,
            "bylaw_page_start": 100,
            "bylaw_page_end": 100
          }
        },
        {
          "provision_label_raw": "c",
          "clause_path": [
            "34.2.1",
            "c"
          ],
          "text": "Retail Store; and",
          "status": "active",
          "citations": {
            "pdf_page_start": 100,
            "pdf_page_end": 100,
            "bylaw_page_start": 100,
            "bylaw_page_end": 100
          }
        },
        {
          "provision_label_raw": "d",
          "clause_path": [
            "34.2.1",
            "d"
          ],
          "text": "Cultural Establishment;",
          "status": "active",
          "citations": {
            "pdf_page_start": 100,
            "pdf_page_end": 100,
            "bylaw_page_start": 100,
            "bylaw_page_end": 100
          }
        },
        {
          "provision_label_raw": "34.2.2",
          "clause_path": [
            "34.2.2"
          ],
          "text": "A minimum of 60% of the ground floor shall be designated to the above uses.",
          "status": "active",
          "citations": {
            "pdf_page_start": 100,
            "pdf_page_end": 100,
            "bylaw_page_start": 100,
            "bylaw_page_end": 100
          }
        },
        {
          "provision_label_raw": "34.2.3",
          "clause_path": [
            "34.2.3"
          ],
          "text": "Map C. Walkable Streets",
          "status": "active",
          "citations": {
            "pdf_page_start": 100,
            "pdf_page_end": 100,
            "bylaw_page_start": 100,
            "bylaw_page_end": 100
          }
        }
      ]
    },
    {
      "order_index": 3,
      "section_label_raw": null,
      "title_label_raw": "REGULATIONS FOR PERMITTED USES",
      "citations": {
        "pdf_page_start": 101,
        "pdf_page_end": 102,
        "bylaw_page_start": 101,
        "bylaw_page_end": 102
      },
      "provisions": [
        {
          "provision_label_raw": "section",
          "text": "All permitted uses in the WF Zone are subject to the following regulations: Minimum: 10 m (32.3 ft) Maximum: 16.5 m (54.1 ft) properties adjacent to Water St Maximum: 24.5 m (80.4 ft) for all other properties.",
          "status": "active",
          "citations": {
            "pdf_page_start": 101,
            "pdf_page_end": 101,
            "bylaw_page_start": 101,
            "bylaw_page_end": 101
          }
        },
        {
          "provision_label_raw": "3",
          "text": "Front or Flankage Yard (See Map F) Maximum: 1.5 m (4.9 ft) on Water St Maximum: 4 m (13.1 ft) on all other streets.",
          "status": "active",
          "citations": {
            "pdf_page_start": 101,
            "pdf_page_end": 101,
            "bylaw_page_start": 101,
            "bylaw_page_end": 101
          }
        },
        {
          "provision_label_raw": "4",
          "text": "Rear or Side Yard A Setback may be permitted but not to exceed 20% of the Lot Width or Lot Depth. “All buildings shall be setback a minimum of 8m (26.2ft) from the ordinary high water mark.”",
          "status": "active",
          "citations": {
            "pdf_page_start": 101,
            "pdf_page_end": 101,
            "bylaw_page_start": 101,
            "bylaw_page_end": 101
          }
        },
        {
          "provision_label_raw": "5",
          "text": "Streetwall Height (See Map G) Maximum: 15.5 m (50.9 ft) on Water St Maximum: 16.5 m (54.1 ft) on all other streets",
          "status": "active",
          "citations": {
            "pdf_page_start": 101,
            "pdf_page_end": 101,
            "bylaw_page_start": 101,
            "bylaw_page_end": 101
          }
        },
        {
          "provision_label_raw": "6",
          "text": "Projections Minimum 1.0 m (3.3 ft) from street line, and Maximum 2.5 m (8.2 ft) projection; OR Within the minimum and maximum range of the existing Buildings on the Block.",
          "status": "active",
          "citations": {
            "pdf_page_start": 101,
            "pdf_page_end": 101,
            "bylaw_page_start": 101,
            "bylaw_page_end": 101
          }
        },
        {
          "provision_label_raw": "7",
          "text": "Building Setback/ Stepback Low-Rise Building: A low-rise building may be setback from the interior lot line. This setback may not exceed 20% of the lot frontage; Mid-Rise Building: Massing for mid-rise Buildings with a height above 13 m (42.6 ft) or the height of the streetwall, the mid-rise portion of a building shall be step-back from the interior lot lines no less than 10% of the lot frontage or 5.5m (18ft); whichever is less. Where a lot has more than one streetline, the greater lot width shall be applied.”",
          "status": "active",
          "citations": {
            "pdf_page_start": 101,
            "pdf_page_end": 101,
            "bylaw_page_start": 101,
            "bylaw_page_end": 101
          }
        },
        {
          "provision_label_raw": "8",
          "text": "Ground Floor Finished Floor Elevation (FFE) Minimum 3.76 m CGVD28 (Canadian Geodetic Vertical Datum 1928) 9. Map F. Streetwall Setbacks 10. Map G. Streetwall Heights",
          "status": "active",
          "citations": {
            "pdf_page_start": 101,
            "pdf_page_end": 102,
            "bylaw_page_start": 101,
            "bylaw_page_end": 102
          }
        }
      ],
      "table_column_headings_raw": [
        "Interior/Corner Lots"
      ]
    },
    {
      "order_index": 4,
      "section_label_raw": "34.4",
      "title_label_raw": "BONUS HEIGHT DEVELOPMENT STANDARDS",
      "citations": {
        "pdf_page_start": 102,
        "pdf_page_end": 104,
        "bylaw_page_start": 102,
        "bylaw_page_end": 104
      },
      "provisions": [
        {
          "provision_label_raw": "34.4.1",
          "clause_path": [
            "34.4.1"
          ],
          "text": "Properties in the DWF Zone are eligible for a Bonus Height subject to the following regulations.",
          "status": "active",
          "citations": {
            "pdf_page_start": 102,
            "pdf_page_end": 102,
            "bylaw_page_start": 102,
            "bylaw_page_end": 102
          }
        },
        {
          "provision_label_raw": "a",
          "clause_path": [
            "34.4.1",
            "a"
          ],
          "text": "The maximum Height as specified on Map D may be exceeded to the maximum bonus Height as specified on Map E.",
          "status": "active",
          "citations": {
            "pdf_page_start": 102,
            "pdf_page_end": 102,
            "bylaw_page_start": 102,
            "bylaw_page_end": 102
          }
        },
        {
          "provision_label_raw": "i",
          "clause_path": [
            "34.4.1",
            "i"
          ],
          "text": "A bonus of up to a maximum Building Height of 24.5m (80.4 ft) for properties fronting on Water St.",
          "status": "active",
          "citations": {
            "pdf_page_start": 102,
            "pdf_page_end": 102,
            "bylaw_page_start": 102,
            "bylaw_page_end": 102
          }
        },
        {
          "provision_label_raw": "ii",
          "clause_path": [
            "34.4.1",
            "ii"
          ],
          "text": "A bonus of up to a maximum Building Height of 32.5m (106.6 ft) for all other properties.",
          "status": "active",
          "citations": {
            "pdf_page_start": 103,
            "pdf_page_end": 103,
            "bylaw_page_start": 103,
            "bylaw_page_end": 103
          }
        },
        {
          "provision_label_raw": "b",
          "clause_path": [
            "34.4.1",
            "b"
          ],
          "text": "Parking Structures are ineligible for a Bonus Height.",
          "status": "active",
          "citations": {
            "pdf_page_start": 103,
            "pdf_page_end": 103,
            "bylaw_page_start": 103,
            "bylaw_page_end": 103
          }
        },
        {
          "provision_label_raw": "34.4.2",
          "clause_path": [
            "34.4.2"
          ],
          "text": "Massing for buildings up to 21.3 m (69.9 ft):",
          "status": "active",
          "citations": {
            "pdf_page_start": 103,
            "pdf_page_end": 103,
            "bylaw_page_start": 103,
            "bylaw_page_end": 103
          }
        },
        {
          "provision_label_raw": "a",
          "clause_path": [
            "34.4.2",
            "a"
          ],
          "text": "The components above the base Building that are a bonus in Height shall be subject to:",
          "status": "active",
          "citations": {
            "pdf_page_start": 103,
            "pdf_page_end": 103,
            "bylaw_page_start": 103,
            "bylaw_page_end": 103
          }
        },
        {
          "provision_label_raw": "i",
          "clause_path": [
            "34.4.2",
            "i"
          ],
          "text": "A minimum 3.0m (9.8ft) Stepback from the base Building on the front façade.",
          "status": "active",
          "citations": {
            "pdf_page_start": 103,
            "pdf_page_end": 103,
            "bylaw_page_start": 103,
            "bylaw_page_end": 103
          }
        },
        {
          "provision_label_raw": "ii",
          "clause_path": [
            "34.4.2",
            "ii"
          ],
          "text": "A minimum 5.5m (18ft) Side Yard Setback or Stepback to ensure adequate separation distances of the upper levels from adjacent properties that may also be eligible for a Height bonus.",
          "status": "active",
          "citations": {
            "pdf_page_start": 103,
            "pdf_page_end": 103,
            "bylaw_page_start": 103,
            "bylaw_page_end": 103
          }
        },
        {
          "provision_label_raw": "iii",
          "clause_path": [
            "34.4.2",
            "iii"
          ],
          "text": "A 45-degree angular planes originating from the top of the flank or rear façade of the base Building that faces abutting properties.",
          "status": "active",
          "citations": {
            "pdf_page_start": 103,
            "pdf_page_end": 103,
            "bylaw_page_start": 103,
            "bylaw_page_end": 103
          }
        },
        {
          "provision_label_raw": "34.4.3",
          "clause_path": [
            "34.4.3"
          ],
          "text": "Massing for Buildings greater than 21.3 m (69.9 ft):",
          "status": "active",
          "citations": {
            "pdf_page_start": 103,
            "pdf_page_end": 103,
            "bylaw_page_start": 103,
            "bylaw_page_end": 103
          }
        },
        {
          "provision_label_raw": "a",
          "clause_path": [
            "34.4.3",
            "a"
          ],
          "text": "The components above the base Building that are a bonus in Height shall be subject to:",
          "status": "active",
          "citations": {
            "pdf_page_start": 103,
            "pdf_page_end": 103,
            "bylaw_page_start": 103,
            "bylaw_page_end": 103
          }
        },
        {
          "provision_label_raw": "i",
          "clause_path": [
            "34.4.3",
            "i"
          ],
          "text": "A minimum 6.0m (19.7ft) Stepback above the base Building or above that portion of the Building that is taller than 21.3 m (69.9 ft) on the front façade.",
          "status": "active",
          "citations": {
            "pdf_page_start": 103,
            "pdf_page_end": 103,
            "bylaw_page_start": 103,
            "bylaw_page_end": 103
          }
        },
        {
          "provision_label_raw": "b",
          "clause_path": [
            "34.4.3",
            "b"
          ],
          "text": "The portion of the Building above 21.3 m (69.9 ft) shall have:",
          "status": "active",
          "citations": {
            "pdf_page_start": 103,
            "pdf_page_end": 103,
            "bylaw_page_start": 103,
            "bylaw_page_end": 103
          }
        },
        {
          "provision_label_raw": "i",
          "clause_path": [
            "34.4.3",
            "i"
          ],
          "text": "A maximum gross floor plate size of 750 sq m (8,072.9 sq ft);",
          "status": "active",
          "citations": {
            "pdf_page_start": 103,
            "pdf_page_end": 103,
            "bylaw_page_start": 103,
            "bylaw_page_end": 103
          }
        },
        {
          "provision_label_raw": "ii",
          "clause_path": [
            "34.4.3",
            "ii"
          ],
          "text": "A minimum 10m (32.8 ft) interior Yard Setbacks; and",
          "status": "active",
          "citations": {
            "pdf_page_start": 103,
            "pdf_page_end": 103,
            "bylaw_page_start": 103,
            "bylaw_page_end": 103
          }
        },
        {
          "provision_label_raw": "iii",
          "clause_path": [
            "34.4.3",
            "iii"
          ],
          "text": "A maximum 25.0m (82 ft) Building width addressing the Street.",
          "status": "active",
          "citations": {
            "pdf_page_start": 103,
            "pdf_page_end": 103,
            "bylaw_page_start": 103,
            "bylaw_page_end": 103
          }
        },
        {
          "provision_label_raw": "34.4.4",
          "clause_path": [
            "34.4.4"
          ],
          "text": "Bonus Height applications are subject to the provisions in the Bonus Height Applications Section of this by-law.",
          "status": "active",
          "citations": {
            "pdf_page_start": 103,
            "pdf_page_end": 103,
            "bylaw_page_start": 103,
            "bylaw_page_end": 103
          }
        },
        {
          "provision_label_raw": "34.4.5",
          "clause_path": [
            "34.4.5"
          ],
          "text": "Map D: Maximum Height 34.4.6 16.5 m (54.1 ft) 24.5 m (80.4 ft)",
          "status": "active",
          "citations": {
            "pdf_page_start": 103,
            "pdf_page_end": 103,
            "bylaw_page_start": 103,
            "bylaw_page_end": 103
          }
        },
        {
          "provision_label_raw": "34.4.7",
          "clause_path": [
            "34.4.7"
          ],
          "text": "Map E: Maximum Bonus Height",
          "status": "active",
          "citations": {
            "pdf_page_start": 104,
            "pdf_page_end": 104,
            "bylaw_page_start": 104,
            "bylaw_page_end": 104
          }
        }
      ]
    },
    {
      "order_index": 5,
      "section_label_raw": "34.5",
      "title_label_raw": "STORM SURGE PROTECTION",
      "citations": {
        "pdf_page_start": 104,
        "pdf_page_end": 104,
        "bylaw_page_start": 104,
        "bylaw_page_end": 104
      },
      "provisions": [
        {
          "provision_label_raw": "34.5.1",
          "clause_path": [
            "34.5.1"
          ],
          "text": "The minimum finished floor elevation (FFE) shall not apply to Parking Structures, Accessory Buildings, or any water related Structures",
          "status": "active",
          "citations": {
            "pdf_page_start": 104,
            "pdf_page_end": 104,
            "bylaw_page_start": 104,
            "bylaw_page_end": 104
          }
        },
        {
          "provision_label_raw": "34.5.2",
          "clause_path": [
            "34.5.2"
          ],
          "text": "Any existing residential use presently below the required elevation may expand, provided the expansion area satisfies the minimum finished floor elevation (FFE) requirements. 24.5m (80.4 ft) 32.5m (106.6 ft)",
          "status": "active",
          "citations": {
            "pdf_page_start": 104,
            "pdf_page_end": 104,
            "bylaw_page_start": 104,
            "bylaw_page_end": 104
          }
        }
      ]
    }
  ],
  "zone_specific_requirements": [],
  "shared_requirement_references": [],
  "content_blocks": [],
  "open_issues": [
    {
      "issue_type": "table_parsing_review",
      "description": "Section 'REGULATIONS FOR PERMITTED USES' contains table-derived provisions extracted from PDF text; verify column alignment against the source PDF before normalization."
    },
    {
      "issue_type": "source_revision_review",
      "description": "Source PDF cover identifies rev 049 updated March 9, 2026, but this zone page header may display rev 048 updated October 24, 2025; verify source revision during QA."
    }
  ],
  "citations": {
    "zone_section": {
      "pdf_page_start": 100,
      "pdf_page_end": 104,
      "bylaw_page_start": 100,
      "bylaw_page_end": 104
    }
  }
}
