{
  "document_metadata": {
    "jurisdiction": "Halifax Regional Municipality",
    "bylaw_name": "Land Use By-law for Eastern Passage/Cow Bay",
    "source_document_path": "docs/eastern-passage-cow-bay-land-use-bylaw.pdf",
    "zone_code": "P-1",
    "zone_name": "COMMUNITY FACILITY",
    "part_label_raw": "PART 22"
  },
  "normalization_policy": {
    "clause_labels_preserved_raw": true,
    "approved_hierarchy_examples": [
      "21(e)",
      "21(ea)",
      "21(ea)(1)"
    ],
    "pending_review_clause_patterns": [
      "22.1",
      "22.2",
      "22.3",
      "22.4",
      "22.5"
    ]
  },
  "permitted_uses": [],
  "requirement_sections": [
    {
      "order_index": 1,
      "section_label_raw": "22.1",
      "title_label_raw": "P-l USES PERMITTED",
      "citations": {
        "pdf_page_start": 90,
        "pdf_page_end": 90,
        "bylaw_page_start": 83,
        "bylaw_page_end": 83
      },
      "provisions": [
        {
          "provision_label_raw": "22.1",
          "text": "P-l USES PERMITTED No development permit shall be issued in any P -l (Community Facility) Zone except for the following uses: Institutional Uses Educational institutions and uses; Denominational institutions and uses; Shared housing use with 10 or fewer bedrooms; (RC-Aug 9/22;E-Sep 15/22) Shared housing with special care; (RC-Aug 9/22;E-Sep 15/22) Fire and police stations; Government offices and public works except transportation maintenance yards; Hospitals Public libraries, museums and galleries; Open Space Uses Public and private parks and playgrounds; Recreation uses; Cemeteries except crematoriums; Day camps; Historic sites and monuments.",
          "status": "active",
          "citations": {
            "pdf_page_start": 90,
            "pdf_page_end": 90,
            "bylaw_page_start": 83,
            "bylaw_page_end": 83
          }
        }
      ]
    },
    {
      "order_index": 2,
      "section_label_raw": "22.2",
      "title_label_raw": "P-l ZONE REQUIREMENTS: INSTITUTIONAL USES",
      "citations": {
        "pdf_page_start": 90,
        "pdf_page_end": 90,
        "bylaw_page_start": 83,
        "bylaw_page_end": 83
      },
      "provisions": [
        {
          "provision_label_raw": "22.2",
          "text": "P-l ZONE REQUIREMENTS: INSTITUTIONAL USES In any P -l Zone, where uses are permitted as Institutional Uses, no development permit shall be issued except in conformity with the following: Minimum Lot Area: central services 10,000 square feet (929 m2) on-site services 30,000 square feet (RC-Feb 19/98;M-Apr 27/98) Minimum Frontage 125 feet (RC-Feb 19/98;M- Apr 27/98) Minimum Front or Flankage Yard 30 feet (9.1 m) Minimum Rear or Side Yard 1/2 the height of the main building Maximum Lot Coverage 50 percent",
          "status": "active",
          "citations": {
            "pdf_page_start": 90,
            "pdf_page_end": 90,
            "bylaw_page_start": 83,
            "bylaw_page_end": 83
          }
        }
      ]
    },
    {
      "order_index": 3,
      "section_label_raw": "22.3",
      "title_label_raw": "P-l ZONE REQUIREMENTS: OPEN SPACE USES",
      "citations": {
        "pdf_page_start": 90,
        "pdf_page_end": 90,
        "bylaw_page_start": 83,
        "bylaw_page_end": 83
      },
      "provisions": [
        {
          "provision_label_raw": "22.3",
          "text": "P-l ZONE REQUIREMENTS: OPEN SPACE USES In any P -l Zone, where uses are permitted as Open Space Uses, no development permit shall be issued except in conformity with the following: Minimum Front or Flankage Yard 15 feet (4.6 m) Minimum Rear or Side Yard 15 feet (4.6 m)",
          "status": "active",
          "citations": {
            "pdf_page_start": 90,
            "pdf_page_end": 90,
            "bylaw_page_start": 83,
            "bylaw_page_end": 83
          }
        }
      ]
    },
    {
      "order_index": 4,
      "section_label_raw": "22.4",
      "title_label_raw": "EXEMPTION: OPEN SPACE USES",
      "citations": {
        "pdf_page_start": 91,
        "pdf_page_end": 91,
        "bylaw_page_start": 84,
        "bylaw_page_end": 84
      },
      "provisions": [
        {
          "provision_label_raw": "22.4",
          "text": "EXEMPTION: OPEN SPACE USES Notwithstanding Subsection 4.1(a), where uses permitted are as Open Space Uses, and where such uses involve no buildings or structures, no development permit shall be required.",
          "status": "active",
          "citations": {
            "pdf_page_start": 91,
            "pdf_page_end": 91,
            "bylaw_page_start": 84,
            "bylaw_page_end": 84
          }
        }
      ]
    },
    {
      "order_index": 5,
      "section_label_raw": "22.5",
      "title_label_raw": "EXEMPTION: INSTITUTIONAL USES",
      "citations": {
        "pdf_page_start": 91,
        "pdf_page_end": 91,
        "bylaw_page_start": 84,
        "bylaw_page_end": 84
      },
      "provisions": [
        {
          "provision_label_raw": "22.5",
          "text": "EXEMPTION: INSTITUTIONAL USES Notwithstanding Section 22.2, where uses are permitted as Institutional Uses, a building may be exempted from a yard requirement in order to permit it to be joined to a building on an adjacent parcel and in this case, all other yard requirements shall apply.",
          "status": "active",
          "citations": {
            "pdf_page_start": 91,
            "pdf_page_end": 91,
            "bylaw_page_start": 84,
            "bylaw_page_end": 84
          }
        }
      ]
    }
  ],
  "content_blocks": [
    {
      "heading_context_raw": null,
      "text": "22.1 P-l USES PERMITTED No development permit shall be issued in any P -l (Community Facility) Zone except for"
    },
    {
      "heading_context_raw": "the following uses:",
      "text": "Institutional Uses Educational institutions and uses; Denominational institutions and uses; Shared housing use with 10 or fewer bedrooms; (RC-Aug 9/22;E-Sep 15/22) Shared housing with special care; (RC-Aug 9/22;E-Sep 15/22) Fire and police stations; Government offices and public works except transportation maintenance yards; Hospitals Public libraries, museums and galleries; Open Space Uses Public and private parks and playgrounds; Recreation uses; Cemeteries except crematoriums; Day camps; Historic sites and monuments. 22.2 P-l ZONE REQUIREMENTS: INSTITUTIONAL USES In any P -l Zone, where uses are permitted as Institutional Uses, no development permit"
    },
    {
      "heading_context_raw": "shall be issued except in conformity with the following:",
      "text": "Minimum Lot Area: central services 10,000 square feet (929 m2) on-site services 30,000 square feet (RC-Feb 19/98;M-Apr 27/98) Minimum Frontage 125 feet (RC-Feb 19/98;M- Apr 27/98) Minimum Front or Flankage Yard 30 feet (9.1 m) Minimum Rear or Side Yard 1/2 the height of the main building Maximum Lot Coverage 50 percent 22.3 P-l ZONE REQUIREMENTS: OPEN SPACE USES In any P -l Zone, where uses are permitted as Open Space Uses, no development permit"
    },
    {
      "heading_context_raw": "shall be issued except in conformity with the following:",
      "text": "Minimum Front or Flankage Yard 15 feet (4.6 m) Minimum Rear or Side Yard 15 feet (4.6 m)"
    },
    {
      "heading_context_raw": "22.4 EXEMPTION: OPEN SPACE USES",
      "text": "Notwithstanding Subsection 4.1(a), where uses permitted are as Open Space Uses, and where such uses involve no buildings or structures, no development permit shall be required."
    },
    {
      "heading_context_raw": "22.5 EXEMPTION: INSTITUTIONAL USES",
      "text": "Notwithstanding Section 22.2, where uses are permitted as Institutional Uses, a building may be exempted from a yard requirement in order to permit it to be joined to a building on an adjacent parcel and in this case, all other yard requirements shall apply."
    }
  ],
  "open_issues": [
    {
      "issue_type": "normalization_review",
      "description": "Clause patterns listed in pending_review_clause_patterns were preserved raw because their hierarchy normalization is not yet approved in this repository context."
    }
  ],
  "citations": {
    "zone_section": {
      "pdf_page_start": 90,
      "pdf_page_end": 91,
      "bylaw_page_start": 83,
      "bylaw_page_end": 84
    }
  }
}
